iotdb_session/Session.py
iotdb_session/SessionExample.py
iotdb_session/__init__.py
iotdb_session/container.py
iotdb_session/test_example.py
iotdb_session/utils/Field.py
iotdb_session/utils/IoTDBConstants.py
iotdb_session/utils/IoTDBRpcDataSet.py
iotdb_session/utils/RowRecord.py
iotdb_session/utils/SessionDataSet.py
iotdb_session/utils/Tablet.py
iotdb_session/utils/__init__.py
iotdb_session_0.10.1-0.1.5.dist-info/LICENSE
iotdb_session_0.10.1-0.1.5.dist-info/METADATA
iotdb_session_0.10.1-0.1.5.dist-info/NOTICE
iotdb_session_0.10.1-0.1.5.dist-info/WHEEL
iotdb_session_0.10.1-0.1.5.dist-info/top_level.txt
iotdb_session_0.10.1-0.1.5.dist-info/RECORD
