Metadata-Version: 2.1
Name: iotdb-session-0.10.1
Version: 0.1.5
Summary: A small iotdb python client
Home-page: https://github.com/JulianFeinauer/iotdb-session-py
Author: Julian Feinauer
Author-email: j.feinauer@pragmaticminds.de
License: UNKNOWN
Platform: UNKNOWN
Classifier: Programming Language :: Python :: 3
Classifier: License :: OSI Approved :: Apache Software License
Classifier: Operating System :: OS Independent
Requires-Python: >=3.6
Requires-Dist: apache-iotdb (==0.10.1)
Requires-Dist: six (==1.15.0)
Requires-Dist: thrift (==0.13.0)
